smartie/__init__.py
smartie/cli.py
smartie/database.py
smartie/device.py
smartie/structures.py
smartie/util.py
smartie/nvme/__init__.py
smartie/nvme/constants.py
smartie/nvme/errors.py
smartie/nvme/linux.py
smartie/nvme/structures.py
smartie/platforms/__init__.py
smartie/platforms/linux.py
smartie/platforms/osx.py
smartie/platforms/win32.py
smartie/scsi/__init__.py
smartie/scsi/errors.py
smartie/scsi/linux.py
smartie/scsi/structures.py
smartie/scsi/windows.py
smartie-4.0.4.dist-info/METADATA
smartie-4.0.4.dist-info/WHEEL
smartie-4.0.4.dist-info/entry_points.txt
smartie-4.0.4.dist-info/licenses/LICENCE
smartie-4.0.4.dist-info/RECORD
