Metadata-Version: 2.3
Name: smartie
Version: 4.0.4
Summary: A pure-python S.M.A.R.T library.
Project-URL: Repository, https://github.com/tktech/smartie
Author-email: Tyler Kennedy <tk@tkte.ch>
License-File: LICENCE
Keywords: hardware,monitor,sensors,smart
Classifier: Development Status :: 4 - Beta
Classifier: Intended Audience :: Developers
Classifier: License :: OSI Approved :: MIT License
Classifier: Operating System :: MacOS :: MacOS X
Classifier: Operating System :: Microsoft :: Windows
Classifier: Operating System :: POSIX :: Linux
Classifier: Programming Language :: Python :: 3.8
Classifier: Programming Language :: Python :: 3.9
Classifier: Programming Language :: Python :: 3.10
Requires-Python: >=3.8
Provides-Extra: cli
Requires-Dist: click>=8.1.7; extra == 'cli'
Requires-Dist: rich>=13.9.4; extra == 'cli'
